intent_kit/__init__.py
intent_kit/types.py
intent_kit/core/__init__.py
intent_kit/core/dag.py
intent_kit/core/exceptions.py
intent_kit/core/traversal.py
intent_kit/core/types.py
intent_kit/core/validation.py
intent_kit/core/context/__init__.py
intent_kit/core/context/adapters.py
intent_kit/core/context/default.py
intent_kit/core/context/fingerprint.py
intent_kit/core/context/policies.py
intent_kit/core/context/protocols.py
intent_kit/evals/__init__.py
intent_kit/evals/run_all_evals.py
intent_kit/evals/run_node_eval.py
intent_kit/evals/test_eval_api.py
intent_kit/nodes/__init__.py
intent_kit/nodes/action.py
intent_kit/nodes/clarification.py
intent_kit/nodes/classifier.py
intent_kit/nodes/extractor.py
intent_kit/services/__init__.py
intent_kit/services/loader_service.py
intent_kit/services/yaml_service.py
intent_kit/services/ai/__init__.py
intent_kit/services/ai/anthropic_client.py
intent_kit/services/ai/base_client.py
intent_kit/services/ai/google_client.py
intent_kit/services/ai/llm_factory.py
intent_kit/services/ai/llm_response.py
intent_kit/services/ai/llm_service.py
intent_kit/services/ai/ollama_client.py
intent_kit/services/ai/openai_client.py
intent_kit/services/ai/openrouter_client.py
intent_kit/services/ai/pricing.py
intent_kit/services/ai/pricing_service.py
intent_kit/services/ai/config/__init__.py
intent_kit/utils/__init__.py
intent_kit/utils/logger.py
intent_kit/utils/perf_util.py
intent_kit/utils/report_utils.py
intent_kit/utils/text_utils.py
intent_kit/utils/type_coercion.py
intent_kit/utils/typed_output.py
intentkit_py-0.7.0.dist-info/licenses/LICENSE
scripts/__init__.py
scripts/check_changelog.py
scripts/dev_coverage.py
scripts/examples.py
scripts/lint.py
scripts/manage_docs.py
scripts/post_commit_amend.py
scripts/security.py
scripts/sync_version.py
scripts/typecheck.py
scripts/validate_codecov.py
intentkit_py-0.7.0.dist-info/METADATA
intentkit_py-0.7.0.dist-info/WHEEL
intentkit_py-0.7.0.dist-info/entry_points.txt
intentkit_py-0.7.0.dist-info/top_level.txt
intentkit_py-0.7.0.dist-info/RECORD
