Metadata-Version: 2.4
Name: intentkit-py
Version: 0.7.0
Summary: An open-source Python library for building intent classification and execution systems that work with any AI backend.
Author-email: Stephen Collins <stephen@stephencollins.tech>
License: MIT
Project-URL: Homepage, https://github.com/Stephen-Collins-tech/intent-kit
Project-URL: Documentation, https://docs.intentkit.io
Project-URL: Repository, https://github.com/Stephen-Collins-tech/intent-kit
Project-URL: Bug Tracker, https://github.com/Stephen-Collins-tech/intent-kit/issues
Classifier: Development Status :: 3 - Alpha
Classifier: Intended Audience :: Developers
Classifier: License :: OSI Approved :: MIT License
Classifier: Operating System :: OS Independent
Classifier: Programming Language :: Python :: 3
Classifier: Programming Language :: Python :: 3.11
Classifier: Programming Language :: Python :: 3.12
Classifier: Topic :: Software Development :: Libraries :: Python Modules
Classifier: Topic :: Scientific/Engineering :: Artificial Intelligence
Requires-Python: >=3.11
License-File: LICENSE
Provides-Extra: all
Requires-Dist: anthropic>=0.54.0; extra == "all"
Requires-Dist: google-genai>=0.1.0; extra == "all"
Requires-Dist: ollama>=0.1.0; extra == "all"
Requires-Dist: openai>=1.0.0; extra == "all"
Requires-Dist: pyyaml>=6.0.2; extra == "all"
Provides-Extra: anthropic
Requires-Dist: anthropic>=0.54.0; extra == "anthropic"
Provides-Extra: google
Requires-Dist: google-genai>=0.1.0; extra == "google"
Provides-Extra: ollama
Requires-Dist: ollama>=0.1.0; extra == "ollama"
Provides-Extra: openai
Requires-Dist: openai>=1.0.0; extra == "openai"
Provides-Extra: yaml
Requires-Dist: pyyaml>=6.0.2; extra == "yaml"
Dynamic: license-file
